pydmp/__init__.py
pydmp/area.py
pydmp/cli.py
pydmp/crypto.py
pydmp/exceptions.py
pydmp/output.py
pydmp/panel.py
pydmp/panel_sync.py
pydmp/profile.py
pydmp/protocol.py
pydmp/status_parser.py
pydmp/status_server.py
pydmp/transport.py
pydmp/transport_sync.py
pydmp/user.py
pydmp/zone.py
pydmp/const/__init__.py
pydmp/const/commands.py
pydmp/const/events.py
pydmp/const/protocol.py
pydmp/const/responses.py
pydmp/const/strings.py
pydmp-1.0.0a2.dist-info/METADATA
pydmp-1.0.0a2.dist-info/WHEEL
pydmp-1.0.0a2.dist-info/entry_points.txt
pydmp-1.0.0a2.dist-info/licenses/LICENSE
pydmp-1.0.0a2.dist-info/RECORD
