Metadata-Version: 2.4
Name: pydmp
Version: 1.0.0a2
Summary: Python library for controlling DMP alarm systems
Author-email: Your Name <your.email@example.com>
License: Apache-2.0
License-File: LICENSE
Keywords: alarm,dmp,home-automation,security
Classifier: Development Status :: 3 - Alpha
Classifier: Intended Audience :: Developers
Classifier: License :: OSI Approved :: Apache Software License
Classifier: Programming Language :: Python :: 3
Classifier: Programming Language :: Python :: 3.10
Classifier: Programming Language :: Python :: 3.11
Classifier: Programming Language :: Python :: 3.12
Classifier: Topic :: Home Automation
Classifier: Topic :: Security
Requires-Python: >=3.10
Provides-Extra: cli
Requires-Dist: click>=8.1; extra == 'cli'
Requires-Dist: pyyaml>=6.0; extra == 'cli'
Requires-Dist: rich>=13.0; extra == 'cli'
Provides-Extra: dev
Requires-Dist: black==24.10.0; extra == 'dev'
Requires-Dist: mypy>=1.5; extra == 'dev'
Requires-Dist: pre-commit>=3.4; extra == 'dev'
Requires-Dist: pytest-asyncio>=0.21; extra == 'dev'
Requires-Dist: pytest-cov>=4.1; extra == 'dev'
Requires-Dist: pytest>=7.4; extra == 'dev'
Requires-Dist: ruff>=0.6; extra == 'dev'
Provides-Extra: docs
Requires-Dist: mike>=2.0; extra == 'docs'
Requires-Dist: mkdocs-material>=9.4; extra == 'docs'
Requires-Dist: mkdocs>=1.5; extra == 'docs'
Requires-Dist: mkdocstrings[python]>=0.24; extra == 'docs'
